priceSearching/__init__.py
priceSearching/priceSearching.py
priceSearching-0.0.2.dist-info/LICENSE
priceSearching-0.0.2.dist-info/METADATA
priceSearching-0.0.2.dist-info/WHEEL
priceSearching-0.0.2.dist-info/top_level.txt
priceSearching-0.0.2.dist-info/RECORD
